linux_mcp_server/__init__.py
linux_mcp_server/__main__.py
linux_mcp_server/audit.py
linux_mcp_server/commands.py
linux_mcp_server/config.py
linux_mcp_server/formatters.py
linux_mcp_server/logging_config.py
linux_mcp_server/parsers.py
linux_mcp_server/server.py
linux_mcp_server/_vendor/__init__.py
linux_mcp_server/connection/__init__.py
linux_mcp_server/connection/ssh.py
linux_mcp_server/tools/__init__.py
linux_mcp_server/tools/logs.py
linux_mcp_server/tools/network.py
linux_mcp_server/tools/processes.py
linux_mcp_server/tools/services.py
linux_mcp_server/tools/storage.py
linux_mcp_server/tools/system_info.py
linux_mcp_server/utils/__init__.py
linux_mcp_server/utils/decorators.py
linux_mcp_server/utils/enum.py
linux_mcp_server/utils/format.py
linux_mcp_server/utils/types.py
linux_mcp_server/utils/validation.py
linux_mcp_server-1.2.1.dist-info/METADATA
linux_mcp_server-1.2.1.dist-info/WHEEL
linux_mcp_server-1.2.1.dist-info/entry_points.txt
linux_mcp_server-1.2.1.dist-info/licenses/LICENSE
linux_mcp_server-1.2.1.dist-info/licenses/licenses/GPL-3.0.txt
linux_mcp_server-1.2.1.dist-info/RECORD
