Metadata-Version: 2.4
Name: linux-mcp-server
Version: 1.2.1
Summary: MCP server for read-only Linux system administration, diagnostics, and troubleshooting
Project-URL: Source code, https://github.com/rhel-lightspeed/linux-mcp-server
Project-URL: Bug Tracker, https://github.com/rhel-lightspeed/linux-mcp-server/issues
Project-URL: Documentation, https://rhel-lightspeed.github.io/linux-mcp-server/
Author: RHEL Lightspeed
License-File: LICENSE
License-File: licenses/GPL-3.0.txt
Classifier: Development Status :: 5 - Production/Stable
Classifier: Environment :: Console
Classifier: Intended Audience :: Developers
Classifier: Intended Audience :: Information Technology
Classifier: Intended Audience :: System Administrators
Classifier: Natural Language :: English
Classifier: Operating System :: POSIX :: Linux
Classifier: Programming Language :: Python :: 3
Classifier: Programming Language :: Python :: 3 :: Only
Classifier: Programming Language :: Python :: 3.10
Classifier: Programming Language :: Python :: 3.11
Classifier: Programming Language :: Python :: 3.12
Classifier: Programming Language :: Python :: 3.13
Classifier: Programming Language :: Python :: 3.14
Classifier: Topic :: System :: Systems Administration
Classifier: Topic :: Utilities
Requires-Python: >=3.10
Requires-Dist: asyncssh[bcrypt]>=2.22.0
Requires-Dist: fastmcp<3,>=2.14.3
Requires-Dist: pydantic-settings>=2.12.0
Requires-Dist: pydantic>=2.12.5
Provides-Extra: gssapi
Requires-Dist: gssapi>=1.2.0; extra == 'gssapi'
